{
    "everyday": false,
    "id": "bus_21",
    "name": "21",
    "schedule_weekend": [
        [
            "8:00",
            "9:10",
            "10:20",
            "18:20",
            "19:24",
            "20:28"
        ],
        [
            "8:10",
            "9:20",
            "10:30",
            "18:30",
            "19:34",
            "20:38"
        ],
        [
            "8:19",
            "9:29",
            "10:39",
            "18:39",
            "19:43",
            "20:46"
        ],
        [
            "8:32",
            "9:42",
            "10:52",
            "18:52",
            "19:56",
            "20:59"
        ],
        [
            "8:40",
            "9:50",
            "10:55",
            "18:55",
            "20:00",
            "21:00"
        ],
        [
            "8:53",
            "10:03",
            "11:08",
            "19:08",
            "20:12",
            "21:13"
        ],
        [
            "8:59",
            "10:09",
            "11:14",
            "19:14",
            "20:18",
            "21:19"
        ],
        [
            "9:07",
            "10:17",
            "11:22",
            "19:22",
            "20:26",
            "21:27"
        ]
    ],
    "stations_weekend": [
        {
            "name": "\u0423\u043b. \u041b\u043e\u043c\u043e\u043d\u043e\u0441\u043e\u0432\u0430 \u043e\u0442\u043f\u0440."
        },
        {
            "name": "\u041f\u0410\u0422\u041f-1 (\u0443\u043b. \u041d\u0435\u0445\u0438\u043d\u0441\u043a\u0430\u044f)"
        },
        {
            "name": "\u0443\u043b. \u041a\u043e\u043b\u043b\u0435\u043a\u0442\u0438\u0432\u043d\u0430\u044f (\u0443\u043b.\u041f\u0441\u043a\u043e\u0432\u0441\u043a\u0430\u044f)"
        },
        {
            "name": "9 \u043a\u043c \u041f\u0441\u043a\u043e\u0432\u0441\u043a\u043e\u0433\u043e \u0448. \u043f\u0440\u0438\u0431."
        },
        {
            "name": "9 \u043a\u043c \u041f\u0441\u043a\u043e\u0432\u0441\u043a\u043e\u0433\u043e \u0448.\u043e\u0442\u043f\u0440."
        },
        {
            "name": "\u0443\u043b. \u041a\u043e\u043b\u043b\u0435\u043a\u0442\u0438\u0432\u043d\u0430\u044f (\u0443\u043b.\u041f\u0441\u043a\u043e\u0432\u0441\u043a\u0430\u044f)"
        },
        {
            "name": "\u041f\u0410\u0422\u041f-1 (\u0443\u043b. \u041d\u0435\u0445\u0438\u043d\u0441\u043a\u0430\u044f)"
        },
        {
            "name": "\u0423\u043b. \u041b\u043e\u043c\u043e\u043d\u043e\u0441\u043e\u0432\u0430 \u043f\u0440\u0438\u0431."
        }
    ],
    "type": "bus"
}